m2_beats2audio-0.9-py3.7-nspkg.pth
m2/beats2audio/__init__.py
m2/beats2audio/cli.py
m2/beats2audio/click.wav
m2/beats2audio/defaults.py
m2/beats2audio/separator.mp3
m2_beats2audio-0.9.dist-info/LICENSE
m2_beats2audio-0.9.dist-info/METADATA
m2_beats2audio-0.9.dist-info/WHEEL
m2_beats2audio-0.9.dist-info/entry_points.txt
m2_beats2audio-0.9.dist-info/namespace_packages.txt
m2_beats2audio-0.9.dist-info/top_level.txt
m2_beats2audio-0.9.dist-info/RECORD
