Metadata-Version: 2.1
Name: m2-beats2audio
Version: 0.9
Summary: Library for producing audios from beats
Home-page: https://github.com/m2march/beats2audio
Author: Martin "March" Miguel
Author-email: m2.march@gmail.com
License: MIT
Platform: UNKNOWN
Requires-Dist: pydub
Requires-Dist: python-gflags
Requires-Dist: python-magic
Requires-Dist: numpy
Requires-Dist: scipy
